<?xml version = '1.0' encoding = 'UTF-8'?>
<Relation class="oracle.dbtools.crest.model.design.logical.Relation" name="r1" directorySegmentName="seg_0" id="1E34FFD6-B1D0-92E8-3404-DEE59837F68A">
<createdBy>victormaestas</createdBy>
<createdTime>2016-04-25 23:30:22 UTC</createdTime>
<ownerDesignName>Conceptual_model</ownerDesignName>
<engineerTo>
<item key="A7AEF09A-FB37-F69E-AEF4-5281000B5876" value="true"/>
</engineerTo>
<identifying>false</identifying>
<optionalSource>true</optionalSource>
<optionalTarget>true</optionalTarget>
<sourceCardinality>*</sourceCardinality>
<sourceEntity>39576A9D-9FC9-228C-42F1-994EC95638D2</sourceEntity>
<targetCardinalityString>*</targetCardinalityString>
<targetEntity>D726A964-32E2-A4D8-5726-54F3FE3C949F</targetEntity>
<transferable>true</transferable>
<deleteRule>NO ACTION</deleteRule>
</Relation>